pypi_cloud/__init__.py
pypi_cloud-0.0.0a0.dist-info/LICENSE
pypi_cloud-0.0.0a0.dist-info/WHEEL
pypi_cloud-0.0.0a0.dist-info/METADATA
pypi_cloud-0.0.0a0.dist-info/RECORD
