Metadata-Version: 2.1
Name: pypi-cloud
Version: 0.0.0a0
Summary: Host a personal PyPi clone in the cloud.
License: Apache-2.0
Keywords: aws
Author: Kyle Finley
Author-email: kyle@finley.sh
Requires-Python: >=3.8,<4.0
Classifier: Development Status :: 1 - Planning
Classifier: Intended Audience :: Developers
Classifier: License :: OSI Approved :: Apache Software License
Classifier: Natural Language :: English
Classifier: Operating System :: OS Independent
Classifier: Programming Language :: Python
Classifier: Programming Language :: Python :: 3
Classifier: Programming Language :: Python :: 3 :: Only
Classifier: Programming Language :: Python :: 3.8
